LICENSE
MANIFEST.in
README.md
requirements.txt
setup.cfg
setup.py
opycleid/__init__.py
opycleid/categoryaction.py
opycleid/knetanalysis.py
opycleid/matrixnets.py
opycleid/musicmonoids.py
opycleid/q_categoryaction.py
opycleid.egg-info/PKG-INFO
opycleid.egg-info/SOURCES.txt
opycleid.egg-info/dependency_links.txt
opycleid.egg-info/requires.txt
opycleid.egg-info/top_level.txt